LICENSE
asyncsteampy/__init__.py
asyncsteampy/chat.py
asyncsteampy/client.py
asyncsteampy/confirmation.py
asyncsteampy/exceptions.py
asyncsteampy/guard.py
asyncsteampy/login.py
asyncsteampy/market.py
asyncsteampy/models.py
asyncsteampy/utils.py
asyncsteampy-0.1.3.dist-info/LICENSE
asyncsteampy-0.1.3.dist-info/WHEEL
asyncsteampy-0.1.3.dist-info/METADATA
asyncsteampy-0.1.3.dist-info/RECORD
