Metadata-Version: 2.1
Name: asyncsteampy
Version: 0.1.3
Summary: Simple library to trade and interact with steam market, webapi, guard
Home-page: https://github.com/somespecialone/asyncsteampy/
License: MIT
Keywords: steam,trade,steamguard,asyncio,steam-market
Author: somespecialone
Author-email: tkachenkodmitriy@yahoo.com
Requires-Python: >=3.10,<4.0
Classifier: Framework :: AsyncIO
Classifier: Intended Audience :: Developers
Classifier: License :: OSI Approved :: MIT License
Classifier: Operating System :: OS Independent
Classifier: Programming Language :: Python :: 3
Classifier: Programming Language :: Python :: 3.10
Classifier: Programming Language :: Python :: 3.11
Classifier: Topic :: Software Development :: Libraries
Classifier: Topic :: Software Development :: Libraries :: Python Modules
Classifier: Typing :: Typed
Requires-Dist: aiohttp (>=3.8.3,<4.0.0)
Requires-Dist: beautifulsoup4 (>=4.10.0,<5.0.0)
Requires-Dist: rsa (>=4.9,<5.0)
Project-URL: Documentation, https://github.com/somespecialone/asyncsteampy/
Project-URL: Repository, https://github.com/somespecialone/asyncsteampy/
